PyMieScatt/CoreShell.py
PyMieScatt/Inverse.py
PyMieScatt/Mie.py
PyMieScatt/__init__.py
PyMieScatt/_version.py
PyMieScatt-1.7.5.4.dist-info/LICENSE.md
PyMieScatt-1.7.5.4.dist-info/METADATA
PyMieScatt-1.7.5.4.dist-info/WHEEL
PyMieScatt-1.7.5.4.dist-info/top_level.txt
PyMieScatt-1.7.5.4.dist-info/RECORD
