Metadata-Version: 2.1
Name: PyMieScatt
Version: 1.7.5.4
Summary: A collection of forward and inverse Mie solving routines based on Bohren and Huffman's Mie Theory derivations.
Home-page: http://air.eece.wustl.edu/people/ben-sumlin/
Author: Benjamin Sumlin
Author-email: bsumlin@wustl.edu
License: MIT
Keywords: Mie Rayleigh scattering absorption extinction light refraction
Platform: UNKNOWN
Classifier: Development Status :: 5 - Production/Stable
Classifier: Intended Audience :: Science/Research
Classifier: Programming Language :: Python :: 3 :: Only
Classifier: Topic :: Scientific/Engineering :: Physics
Requires-Dist: numpy
Requires-Dist: scipy
Requires-Dist: matplotlib
Requires-Dist: shapely
